dask_snowflake/__init__.py
dask_snowflake/core.py
dask_snowflake/tests/test_core.py
dask_snowflake-0.3.4.dist-info/licenses/LICENSE
dask_snowflake-0.3.4.dist-info/METADATA
dask_snowflake-0.3.4.dist-info/WHEEL
dask_snowflake-0.3.4.dist-info/top_level.txt
dask_snowflake-0.3.4.dist-info/RECORD
