Metadata-Version: 2.4
Name: dask-snowflake
Version: 0.3.4
Summary: Dask + Snowflake intergration
Maintainer: James Bourbeau
Maintainer-email: james@coiled.io
License: BSD
Requires-Python: >=3.9
License-File: LICENSE
Requires-Dist: dask>=2024.3.0
Requires-Dist: distributed
Requires-Dist: snowflake-connector-python[pandas]>=2.6.0
Requires-Dist: snowflake-sqlalchemy
Dynamic: description
Dynamic: description-content-type
Dynamic: license
Dynamic: license-file
Dynamic: maintainer
Dynamic: maintainer-email
Dynamic: requires-dist
Dynamic: requires-python
Dynamic: summary
